mazepa/__init__.py
mazepa/click_interface.py
mazepa/executor.py
mazepa/job.py
mazepa/queue.py
mazepa/scheduler.py
mazepa/serialization.py
mazepa-0.1.5.dist-info/LICENSE
mazepa-0.1.5.dist-info/METADATA
mazepa-0.1.5.dist-info/WHEEL
mazepa-0.1.5.dist-info/top_level.txt
mazepa-0.1.5.dist-info/RECORD
