Metadata-Version: 2.1
Name: mazepa
Version: 0.1.5
Summary: A tool for efficient scheduling of independent tasks to remote workers
Home-page: https://github.com/supersergiy/mazepa
Author: Sergiy Popovych
Author-email: sergiy.popovich@gmail.com
License: UNKNOWN
Platform: UNKNOWN
License-File: LICENSE
Requires-Dist: boto3
Requires-Dist: click
Requires-Dist: task-queue
Requires-Dist: tenacity
